user_management_common_timesheet_mfdenison_hopkinsep/__init__.py
user_management_common_timesheet_mfdenison_hopkinsep/database/__init__.py
user_management_common_timesheet_mfdenison_hopkinsep/database/database.py
user_management_common_timesheet_mfdenison_hopkinsep/models/__init__.py
user_management_common_timesheet_mfdenison_hopkinsep/models/models.py
user_management_common_timesheet_mfdenison_hopkinsep/models/serializers.py
user_management_common_timesheet_mfdenison_hopkinsep/templates/__init__.py
user_management_common_timesheet_mfdenison_hopkinsep/utils/__init__.py
user_management_common_timesheet_mfdenison_hopkinsep/utils/utils.py
user_management_common_timesheet_mfdenison_hopkinsep-0.0.7.dist-info/METADATA
user_management_common_timesheet_mfdenison_hopkinsep-0.0.7.dist-info/WHEEL
user_management_common_timesheet_mfdenison_hopkinsep-0.0.7.dist-info/top_level.txt
user_management_common_timesheet_mfdenison_hopkinsep-0.0.7.dist-info/RECORD
